{
  "realm": "ecommerce",
  "enabled": true,
  "displayName": "Ecommerce Microservices",
  "registrationAllowed": false,
  "loginWithEmailAllowed": true,
  "duplicateEmailsAllowed": false,
  "resetPasswordAllowed": false,
  "rememberMe": false,

  "roles": {
    "realm": [
      {
        "name": "ROLE_ADMIN",
        "description": "Full administrative access to the ecommerce platform"
      },
      {
        "name": "ROLE_ORDER_MANAGER",
        "description": "Can manage and inspect orders"
      },
      {
        "name": "ROLE_CUSTOMER_SUPPORT",
        "description": "Can inspect customer-related information"
      }
    ]
  },

  "clients": [
    {
      "clientId": "ecommerce-gateway",
      "name": "Ecommerce Gateway BFF",
      "description": "Confidential OIDC client for gateway-service BFF login. Browser keeps only the Spring SESSION cookie; tokens stay server-side and access tokens are relayed downstream.",
      "enabled": true,
      "protocol": "openid-connect",
      "publicClient": false,
      "bearerOnly": false,
      "standardFlowEnabled": true,
      "implicitFlowEnabled": false,
      "directAccessGrantsEnabled": false,
      "serviceAccountsEnabled": false,
      "clientAuthenticatorType": "client-secret",
      "secret": "dev-gateway-secret",

      "rootUrl": "http://localhost:8222",
      "adminUrl": "http://localhost:8222",
      "baseUrl": "http://localhost:8222",

      "redirectUris": [
        "http://localhost:8222/login/oauth2/code/keycloak",
        "http://localhost:5173",
        "http://localhost:5173/*"
      ],

      "webOrigins": [
        "http://localhost:8222",
        "http://localhost:5173"
      ],

      "frontchannelLogout": false,

      "attributes": {
        "post.logout.redirect.uris": "+"
      },

      "protocolMappers": [
        {
          "name": "realm roles",
          "protocol": "openid-connect",
          "protocolMapper": "oidc-usermodel-realm-role-mapper",
          "consentRequired": false,
          "config": {
            "multivalued": "true",
            "userinfo.token.claim": "true",
            "id.token.claim": "true",
            "access.token.claim": "true",
            "claim.name": "realm_access.roles",
            "jsonType.label": "String"
          }
        },
        {
          "name": "preferred username",
          "protocol": "openid-connect",
          "protocolMapper": "oidc-usermodel-property-mapper",
          "consentRequired": false,
          "config": {
            "userinfo.token.claim": "true",
            "id.token.claim": "true",
            "access.token.claim": "true",
            "claim.name": "preferred_username",
            "jsonType.label": "String",
            "user.attribute": "username"
          }
        },
        {
          "name": "email",
          "protocol": "openid-connect",
          "protocolMapper": "oidc-usermodel-property-mapper",
          "consentRequired": false,
          "config": {
            "userinfo.token.claim": "true",
            "id.token.claim": "true",
            "access.token.claim": "true",
            "claim.name": "email",
            "jsonType.label": "String",
            "user.attribute": "email"
          }
        },
        {
          "name": "given name",
          "protocol": "openid-connect",
          "protocolMapper": "oidc-usermodel-property-mapper",
          "consentRequired": false,
          "config": {
            "userinfo.token.claim": "true",
            "id.token.claim": "true",
            "access.token.claim": "true",
            "claim.name": "given_name",
            "jsonType.label": "String",
            "user.attribute": "firstName"
          }
        },
        {
          "name": "family name",
          "protocol": "openid-connect",
          "protocolMapper": "oidc-usermodel-property-mapper",
          "consentRequired": false,
          "config": {
            "userinfo.token.claim": "true",
            "id.token.claim": "true",
            "access.token.claim": "true",
            "claim.name": "family_name",
            "jsonType.label": "String",
            "user.attribute": "lastName"
          }
        }
      ]
    },
    {
      "clientId": "ecommerce-internal",
      "name": "Ecommerce Internal Services",
      "description": "Confidential client reserved for future machine-to-machine communication between internal services.",
      "enabled": true,
      "protocol": "openid-connect",
      "publicClient": false,
      "bearerOnly": false,
      "standardFlowEnabled": false,
      "implicitFlowEnabled": false,
      "directAccessGrantsEnabled": false,
      "serviceAccountsEnabled": true,
      "clientAuthenticatorType": "client-secret",
      "secret": "dev-internal-secret"
    }
  ],

  "users": [
    {
      "username": "admin",
      "enabled": true,
      "emailVerified": true,
      "firstName": "Admin",
      "lastName": "User",
      "email": "admin@ecommerce.local",
      "credentials": [
        {
          "type": "password",
          "value": "admin",
          "temporary": false
        }
      ],
      "realmRoles": [
        "ROLE_ADMIN",
        "ROLE_ORDER_MANAGER",
        "ROLE_CUSTOMER_SUPPORT"
      ]
    },
    {
      "username": "orders",
      "enabled": true,
      "emailVerified": true,
      "firstName": "Order",
      "lastName": "Manager",
      "email": "orders@ecommerce.local",
      "credentials": [
        {
          "type": "password",
          "value": "orders",
          "temporary": false
        }
      ],
      "realmRoles": [
        "ROLE_ORDER_MANAGER"
      ]
    },
    {
      "username": "support",
      "enabled": true,
      "emailVerified": true,
      "firstName": "Support",
      "lastName": "User",
      "email": "support@ecommerce.local",
      "credentials": [
        {
          "type": "password",
          "value": "support",
          "temporary": false
        }
      ],
      "realmRoles": [
        "ROLE_CUSTOMER_SUPPORT"
      ]
    }
  ]
}
